py_lap_solver/__init__.py
py_lap_solver/_batched_scipy_lap.cp312-win_amd64.pyd
py_lap_solver/_lap1015.cp312-win_amd64.pyd
py_lap_solver/base.py
py_lap_solver/solvers/__init__.py
py_lap_solver/solvers/batched_scipy_solver.py
py_lap_solver/solvers/lap1015_solver.py
py_lap_solver/solvers/registry.py
py_lap_solver/solvers/scipy_solver.py
py_lap_solver-0.1.4.dist-info/METADATA
py_lap_solver-0.1.4.dist-info/WHEEL
py_lap_solver-0.1.4.dist-info/licenses/LICENSE
py_lap_solver-0.1.4.dist-info/RECORD
