Metadata-Version: 2.2
Name: py-lap-solver
Version: 0.1.4
Summary: Unified Python framework for Linear Assignment Problem solvers
Author-Email: Nikita Pond <nikita.pond@icloud.com>
License: GPL-3.0-or-later
Classifier: Development Status :: 3 - Alpha
Classifier: Intended Audience :: Science/Research
Classifier: License :: OSI Approved :: GNU General Public License v3 or later (GPLv3+)
Classifier: Programming Language :: Python :: 3
Classifier: Programming Language :: Python :: 3.8
Classifier: Programming Language :: Python :: 3.9
Classifier: Programming Language :: Python :: 3.10
Classifier: Programming Language :: Python :: 3.11
Classifier: Programming Language :: Python :: 3.12
Classifier: Programming Language :: C++
Classifier: Topic :: Scientific/Engineering
Project-URL: Homepage, https://github.com/nikitapond/py-lap-solver
Project-URL: Repository, https://github.com/nikitapond/py-lap-solver
Requires-Python: >=3.8
Requires-Dist: numpy>=1.20.0
Requires-Dist: scipy>=1.7.0
Provides-Extra: test
Requires-Dist: pytest>=7.0; extra == "test"
Provides-Extra: dev
Requires-Dist: pytest>=7.0; extra == "dev"
Requires-Dist: black; extra == "dev"
Requires-Dist: ruff; extra == "dev"
Requires-Dist: cibuildwheel>=2.16.0; extra == "dev"
Requires-Dist: build; extra == "dev"
